perplexity_client/__init__.py
perplexity_client/client.py
perplexity_client/exceptions.py
perplexity_client-0.1.0.dist-info/LICENSE
perplexity_client-0.1.0.dist-info/METADATA
perplexity_client-0.1.0.dist-info/WHEEL
perplexity_client-0.1.0.dist-info/RECORD
