Metadata-Version: 2.1
Name: perplexity-client
Version: 0.1.0
Summary: Unofficial Perplexity.ai API Client
License: MIT
Author: Daniel Klic
Author-email: daniel.klic96@gmail.com
Requires-Python: >=3.10,<4.0
Classifier: License :: OSI Approved :: MIT License
Classifier: Programming Language :: Python :: 3
Classifier: Programming Language :: Python :: 3.10
Classifier: Programming Language :: Python :: 3.11
Classifier: Programming Language :: Python :: 3.12
Requires-Dist: requests (>=2.31.0,<3.0.0)
